[
    {
        "no": 235,
        "heading": "S S / S 5 (By W Sorrow)",
        "sub_heading": "Gbo ohun mi, Oluwa",
        "bible_verse": "- Ps. 27 : 7.",
        "intro": "",
        "title": "MO ri ayọ n'nu 'banujẹ,",
        "category": "ORIN IRONUPIWADA",
        "tune": "",
        "lyrics": [
            {
                "stanza": "1",
                "lyric": "MO ri ayọ n'nu 'banujẹ,\nOgun fun irora;\nMo r'ọjọ nla t'o dara,\nT'o ran lẹhin ojo;\nMo r'ẹka  'mularada,\nNibi isun ki ikoro.\n",
                "Egbe": "Ileri jẹjẹ t'a se)\nFun ẹni ti n jaya  )2ce"
            },
            {
                "stanza": "2",
                "lyric": "Ninu irin ajo mi,\nMo ba Jesu pade;\nTi o f'ọkan mi balẹ,\nLati ri anu gba;\nAnu ti n ko le gbagbe,\nIf'aya balẹ nla.\n",
                "Egbe": "Ileri jẹjẹ t'a se"
            },
            {
                "stanza": "3",
                "lyric": "Mo ti ri sinu ẹsẹ;\nFitila mi ku tan;\nNipa anu Ọlọrun,\nMo d'ẹni ti n sọji;\nAnu rẹ ra mi pada,\nO  fi ireti fun mi\n",
                "Egbe": "Ileri jẹjẹ t'a se"
            },
            {
                "stanza": "4",
                "lyric": "Ẹyin Ijọ Séráfù,\nẸ jọ ma jafara;\nẸ jẹ ka damure wa,\nK'ina wa si ma tan;\nAmure ko gbọdọ tu,\nIna ko gbọdọ ku\n",
                "Egbe": "Ileri jẹjẹ t'a se)\nFun ẹni ti n jaya  )2ce\nAMIN."
            }
        ],
        "song_tag": "(FE225)"
    },
    {
        "no": 236,
        "heading": "C.M.S. 187 H.C. 117 t.S. 43",
        "sub_heading": "Ba mi yo, mo ri aguntan mi.",
        "bible_verse": "- Luku. 15 : 6.",
        "intro": "",
        "title": "MỌKANDILỌGỌRUN dubule jẹ,",
        "category": "ORIN IRONUPIWADA",
        "tune": "Ipile ti Jesu fi lele",
        "lyrics": [
            {
                "stanza": "1",
                "lyric": "MỌKANDILỌGỌRUN dubule jẹ,\nLabẹ oji nin' agbo;\nSugbọn ọkan jẹ lọ or'oke,\nJina s'ilekun wura;\nJina rere l' or' oke sisa,\nJina rere s'Olus' aguntan."
            },
            {
                "stanza": "2",
                "lyric": "Mọkandilọgọrun Tirẹ leyi:\nJesu, wọn ko ha to fun O?”\nOlus'-aguntan dahun, “Temi yi,\nTi sako lọdọ mi;\nB'ọna tilẹ ri palapala,\nN ó w'aginju lọ w'aguntan mi."
            },
            {
                "stanza": "3",
                "lyric": "Ọkan nin' awọn t'a  ra pada,\nKo mọ jinjin omi na;\nAti duru oru ti Jesu kọja,\nK'o to r'aguntan Rẹ he;\nL'aginju rere l'o gbọ 'gbe re,\nO ti rẹ tan, o si ti ku tan."
            },
            {
                "stanza": "4",
                "lyric": "Nibo n'iro ẹjẹ ni ti wa,\nT'o f'ọna or' oke han?”\n“A ta silẹ f'ẹnikan t'o sako,\nK'Olusaguntan to mu pada”\nJesu, kil'o gun ọwọ Rẹ bẹẹ?”\n“Ẹgun pupọ l'o gun mi nibe."
            },
            {
                "stanza": "5",
                "lyric": "Sugbọn ni gbogbo ori oke,\nAti l'ori  apata,\nIgbe ta l'oke ọrun wi pé,\n“Yọ, mo r'aguntan mi he.”\nY' itẹ ka l'awọn angẹl n gba,\n“Yọ, Jesu m'ohun Tirẹ pada.\nAMIN."
            }
        ],
        "song_tag": "(FE256)"
    },
    {
        "no": 237,
        "heading": "C.M.S. 147 7.7.7.",
        "sub_heading": "Jeki nwon wipe, Da awon enia Re si, Oluwa, ma si se fi ini Re fun egan.",
        "bible_verse": "- Joeli 2 : 17.",
        "intro": "",
        "title": "Jesu, l'ọjọ anu yi,",
        "category": "ORIN IRONUPIWADA",
        "tune": "",
        "lyrics": [
            {
                "stanza": "1",
                "lyric": "Jesu, l'ọjọ anu yi,\nKi akoko to kọja,\nA wolẹ ni ekun wa."
            },
            {
                "stanza": "2",
                "lyric": "Oluwa, m'ẹkun gbọn wa,\nFi ẹru kun aya wa,\nKi ọjọ iku to de."
            },
            {
                "stanza": "3",
                "lyric": "Tu Ẹmi Rẹ s'ọkan wa,\nL'ẹnu ọna Rẹ la n ke;\nK'ilẹkun anu to se."
            },
            {
                "stanza": "4",
                "lyric": "Tori waya-ija Rẹ,\nTori ogun-ẹjẹ Rẹ,\nTori iku Rẹ fun wa."
            },
            {
                "stanza": "5",
                "lyric": "Tor' ẹkun kikoro Rẹ,\nLori Jerusalẹmu,\nMa jẹ ka gan ifẹ Rẹ"
            },
            {
                "stanza": "6",
                "lyric": "Iwọ Onidajọ wa,\n'Gbat' oju wa ba ri Ọ,\nFun wa n'ipo lọdọ Rẹ."
            },
            {
                "stanza": "7",
                "lyric": "Ifẹ Rẹ l'a sinmi le,\nN'ile wa l'oke l'a o mọ,\nB'ifẹ naa ti tobi to.\nAMIN."
            }
        ],
        "song_tag": "(FE257)"
    },
    {
        "no": 238,
        "heading": "C.M.S. 152 t.H.C 27 tabi A. & M. 101, S.M.",
        "sub_heading": "Emi korira ara mi, mo si ronupiwada se toto ati ninu ekuru ati eru.",
        "bible_verse": "- Jobu 42 : 6.",
        "intro": "",
        "title": "ALAIMO  ni emi,",
        "category": "ORIN IRONUPIWADA",
        "tune": "",
        "lyrics": [
            {
                "stanza": "1",
                "lyric": "ALAIMO  ni emi,\nOlọrun oluwa!\nEmi ha gbọdọ sunmọ Ọ,\nT'emi t'ẹru ẹsẹ?"
            },
            {
                "stanza": "2",
                "lyric": "Ẹru ẹsẹ yi n pa,\nỌkan buburu mi;\nYio ha si ti buru to,\nL'oju Rẹ mimọ ni!"
            },
            {
                "stanza": "3",
                "lyric": "Emi o ha si ku,\nNi alainireti?\nMo r'ayọ ninu iku Rẹ,\nFun otosi b'emi."
            },
            {
                "stanza": "4",
                "lyric": "Ẹjẹ ni ti o ta,\nT'ise or'ọfẹ Rẹ;\nLe w'ẹlẹsẹ, t'o buru ju,\nLe m'ọkan lile rọ."
            },
            {
                "stanza": "5",
                "lyric": "Mo wolẹ l'ẹsẹ Rẹ,\nJọ k'O dariji mi;\nNihin l'emi o wa titi,\n'Wọ o wi pé, “Dide.”"
            }
        ],
        "song_tag": "(FE258)"
    },
    {
        "no": 239,
        "heading": "C.M.S. 146 t.H.C. 247, DSM",
        "sub_heading": "E mu gbogbo ihamora Olorun wo",
        "bible_verse": "- Efe 6 : 11.",
        "intro": "",
        "title": "JESU, agbara mi,",
        "category": "ORIN IRONUPIWADA",
        "tune": "",
        "lyrics": [
            {
                "stanza": "1",
                "lyric": "JESU, agbara mi,\nIwọ l'aniyan mi,\nEmi fi igbagbọ woke;\nIwọ l'o n gbadura,\nJẹ ki n duro de Ọ,\nKi n le se ifẹ Rẹ,\nKi iwọ Olodumare,\nK'o sọ mi di ọtun."
            },
            {
                "stanza": "2",
                "lyric": "Fun mi l'ọkan 'rẹlẹ,\nTi 'ma sẹ ara rẹ;\nTi n tẹmọlẹ, ti ko naani,\nIkẹkun Satani;\nỌkan t'ara rẹ mọ,\nIrora at'isẹ;\nT'o n fi suuru at' igboya\nRu agbelebu rẹ."
            },
            {
                "stanza": "3",
                "lyric": "Fun mi l'ẹru ọrun,\nOju to mu hanhan;\nT' yo wo Ọ n gb'ẹsẹ sunmọle,\nK'o ri b'Esu ti n sa;\nFun mi ni ẹmi ni,\nT'o ti pese tẹlẹ;\nẸmi t'o n duro gangan lai\nT'o n f'adura sọna"
            },
            {
                "stanza": "4",
                "lyric": "Mo gbẹkẹl' ọrọ Rẹ,\n'Wọ l'o leri fun mi;\nIranwọ at'igbala mi,\nY'o t'ọdọ Rẹ wa se,\nSa jẹ ki n le duro.\nK'ireti mi ma yẹ,\nTit' Iwọ o fi m'ọkan mi,\nWọ 'nu isinmi Rẹ.\nAMIN."
            }
        ],
        "song_tag": "(FE259)"
    },
    {
        "no": 240,
        "heading": "C.M.S. 186 H.C. S.M.",
        "sub_heading": "OLuwa, mu ise Re soji",
        "bible_verse": "- Hab 3 : 2",
        "intro": "",
        "title": "JI 'sẹ Rẹ nde, Jesu!",
        "category": "ORIN IRONUPIWADA",
        "tune": "",
        "lyrics": [
            {
                "stanza": "1",
                "lyric": "JI 'sẹ Rẹ nde, Jesu!\nFi agbara Rẹ han!\nFọ'hun t'o le j'oku dide!\nMu k'eniyan rẹ gbọ."
            },
            {
                "stanza": "2",
                "lyric": "Ji'sẹ Rẹ nde, Jesu!\nTọ orun iku yi!\nFi Ẹmi agbara nla Rẹ,\nJi ọkan ti n togbe"
            },
            {
                "stanza": "3",
                "lyric": "Ji'sẹ Rẹ nde, Jesu!\nMu k'oungbẹ Rẹ gbẹ wa:\nSi mu k'ebi  pa ọkan wa,\nFun Ounjẹ iye naa."
            },
            {
                "stanza": "4",
                "lyric": "Ji'sẹ Rẹ nde Jesu!\nGbe orukọ Rẹ ga;\nMu k'ifẹ Rẹ kun ọkan wa,\nNipa Ẹmi Mimọ"
            },
            {
                "stanza": "5",
                "lyric": "Ji'sẹ Rẹ nde, Jesu,\nRọ'jo itura Rẹ;\nOgo y'o jẹ Tirẹ nikan,\nK'ibukun jẹ tiwa\nAMIN."
            }
        ],
        "song_tag": "(FE260)"
    },
    {
        "no": 241,
        "heading": "C.M.S. 182 H.C. 377 8.5.8.3.",
        "sub_heading": "Enikeni ti o ba nsin mi ki o ma to mi lehin; nibiti mo ba wa, nibe ni iranse mi yio ma gbe pelu",
        "bible_verse": "- John 12:26",
        "intro": "",
        "title": "ARẸ mu o ayé su ọ,",
        "category": "ORIN IRONUPIWADA",
        "tune": "",
        "lyrics": [
            {
                "stanza": "1",
                "lyric": "ARẸ mu o ayé su ọ,\nLala pọ fun ọ?\nJesu ni, 'Wa si ọdọ mi,\nK'o sinmi."
            },
            {
                "stanza": "2",
                "lyric": "Ami wo l'emi o fi mọ,\nPe Oun l'o n pe mi?\nAm' iso wa lọwọ, ati ẹsẹ Rẹ"
            },
            {
                "stanza": "3",
                "lyric": "O ha ni ade bi Ọba,\nTi mo le fi mọ?\nTotọ, ade wa lori Rẹ,\nT' ẹgun ni"
            },
            {
                "stanza": "4",
                "lyric": "Bi mo ba ri, bi mo tẹle,\nKini ere mi?\nỌpọlọpọ iya ati\n'Banujẹ"
            },
            {
                "stanza": "5",
                "lyric": "Bi mo tẹle tit' ayé mi,\nKini n ó ri gba?\nẸkun a dopin, o sinmi,\nTit' ayé."
            },
            {
                "stanza": "6",
                "lyric": "Bi mo bere pe ki O gbami\nY'o kọ fun mi bi?\nB'ọrun at'ayé n kọja lọ,\nKo jẹ kọ."
            },
            {
                "stanza": "7",
                "lyric": "Bi mo ba ri, ti mo n tẹle,\nY'o ha bukun mi?\nAwọn ogun ọrun wi pé,\nYio se.\nAMIN."
            }
        ],
        "song_tag": "(FE261)"
    },
    {
        "no": 242,
        "heading": "C.M.S. 142 t.H.C. 246 SM",
        "sub_heading": "Jesu sokun",
        "bible_verse": "- John 11 : 35",
        "intro": "",
        "title": "KRISTI sun f'ẹlẹsẹ,",
        "category": "ORIN IRONUPIWADA",
        "tune": "",
        "lyrics": [
            {
                "stanza": "1",
                "lyric": "KRISTI sun f'ẹlẹsẹ,\nOju wa o gbẹ bi?\nK'omi ronu at'ikanu,\nTu jade l'oju wa."
            },
            {
                "stanza": "2",
                "lyric": "Ọmọ Ọlọrun n sun,\nAngẹli siju wo!\nK'o damu, iwọ ọkan mi,\nO d'omi ni fun ọ."
            },
            {
                "stanza": "3",
                "lyric": "O sun k'awa k'o sun,\nẸsẹ bere ẹkun;\nỌrun nikan ni ko s'ẹsẹ,\nNibẹ ni ko s'ẹkun.\n"
            }
        ],
        "song_tag": "(FE262)"
    },
    {
        "no": 243,
        "heading": "C.M.S. 143 H.C. 548 t.H.C. 191 8.7.",
        "sub_heading": "Loto emi ti gbo Efraimu npohunrere ara re",
        "bible_verse": "- Jer. 31 : 18.",
        "intro": "",
        "title": "OLUWA, ma moju kuro,",
        "category": "ORIN IRONUPIWADA",
        "tune": "",
        "lyrics": [
            {
                "stanza": "1",
                "lyric": "OLUWA, ma moju kuro,\nL'ọdọ emi t'o n yilẹ;\nTi n sọkun ẹsẹ ayé mi,\nN'itẹ anu ifẹ Rẹ."
            },
            {
                "stanza": "2",
                "lyric": "Ma ba mi lọ sinu 'dajọ,\nBi ẹsẹ mi ti pọ to;\nNitori mo mọ daju pe,\nEmi ko wa lailẹbi."
            },
            {
                "stanza": "3",
                "lyric": "Iwọ mọ, ki n to jẹwọ rẹ,\nBi mo ti n se layé mi;\nAt' iwa isinsin yii mi,\nGbogbo rẹ l'O kiyesi."
            },
            {
                "stanza": "4",
                "lyric": "Emi ko ni f’ atunwi se,\nOhun ti mo fẹ tọrọ;\nNi iwọ mọ ki n to bere,\nAnu ni lọpọlọpọ."
            },
            {
                "stanza": "5",
                "lyric": "Anu Oluwa ni mo fẹ,\nEyi l’opin gbogbo rẹ;\nTori anu ni mo n tọrọ,\nJẹ ki n ri anu gba\n"
            }
        ],
        "song_tag": "(FE263)"
    },
    {
        "no": 244,
        "heading": "C.M.S. 144 H.C. 147 C.M.",
        "sub_heading": "E je ki a fi igboya wa si ibi ite ore-ofe",
        "bible_verse": "- Heb. 4 : 16.",
        "intro": "",
        "title": "ỌKAN mi sunmọ ‘tẹ anu,",
        "category": "ORIN IRONUPIWADA",
        "tune": "",
        "lyrics": [
            {
                "stanza": "1",
                "lyric": "ỌKAN mi sunmọ ‘tẹ anu,\nNibi Jesu n gb’ẹbẹ;\nF’irẹlẹ wolẹ l’ẹsẹ Rẹ,\n‘Wọ ko le gbe nibẹ."
            },
            {
                "stanza": "2",
                "lyric": "Ileri Rẹ ni ẹbẹ mi,\nEyi ni mo mu wa;\nIwọ n pe ọkan t’ẹru npa,\nBi emi Oluwa."
            },
            {
                "stanza": "3",
                "lyric": "Ẹru ẹsẹ wọ mi l’ọrun,\nẸsẹ n sẹ mi n’isẹ;\nOgun l’ode, ẹru ninu,\nMo wa isinmi mi"
            },
            {
                "stanza": "4",
                "lyric": "Se Apata at’Asa mi,\nKi n fi Ọ se abo;\nKi n doju ti Olufisun,\nKi n sọ pe Kristi ku."
            },
            {
                "stanza": "5",
                "lyric": "Ifẹ Iyanu! Iwọ ku,\nIwọ ru itiju;\nKi ẹlẹsẹ b’iru emi,\nLe bẹ l’orukọ Rẹ.\nAMIN."
            }
        ],
        "song_tag": "(FE264)"
    },
    {
        "no": 245,
        "heading": "C.M.S. 145 H.C. 145 7s.",
        "sub_heading": "Olorun sanu fun mi, elese",
        "bible_verse": "- Luku. 18 : 13.",
        "intro": "",
        "title": "ỌKAN mi sunmọ ‘tẹ anu,",
        "category": "ORIN IRONUPIWADA",
        "tune": "",
        "lyrics": [
            {
                "stanza": "1",
                "lyric": "ẸLẸSẸ; mo n fẹ ‘bukun;\nOnde: mo n fẹ d’omnira;\nAlarẹ: mo n fẹ ‘sinmi,\n“Ọlọrun, saanu fun mi”."
            },
            {
                "stanza": "2",
                "lyric": "Ire kan emi ko ni,\nẸsẹ sa l’o yi mi ka,\nEyi nikan l’ẹbẹ mi,\n“Ọlọrun, saanu fun mi”."
            },
            {
                "stanza": "3",
                "lyric": "Irobinujẹ ọkan!\nNko gbọdọ gboju s’oke;\nIwọ sa mọ ẹdun mi;\n“Ọlọrun, saanu fun mi"
            },
            {
                "stanza": "4",
                "lyric": "Ọkan ẹsẹ mi yi n fẹ,\nSa wa sinmi laya Rẹ;\nLat’ oni, mo di Tirẹ,\n“Ọlọrun, saanu fun mi"
            },
            {
                "stanza": "5",
                "lyric": "Ẹnikan mbẹ l’or’ itẹ,\nNinu Rẹ nikansoso,\nN’ ireti at’ẹbẹ mi;\n“Ọlọrun, saanu fun mi”"
            },
            {
                "stanza": "6",
                "lyric": "Oun o gba ọran mi ro,\nOun ni Alagbawi mi;\nNitori Tirẹ nikan;\n“Ọlọrun, saanu fun mi”.\nAMIN."
            }
        ],
        "song_tag": "(FE265)"
    },
    {
        "no": 246,
        "heading": "C.M.S. 149 H.C. 155 t.H.C. 94, S.M.",
        "sub_heading": "Awon sokun nigbati awa ranti Sioni.",
        "bible_verse": "- Ps. 132 : 1.",
        "intro": "",
        "title": "ỌKAN mi sunmọ ‘tẹ anu,",
        "category": "ORIN IRONUPIWADA",
        "tune": "",
        "lyrics": [
            {
                "stanza": "1",
                "lyric": "JINA s’ile ọrun,\nS’ọkan aya Baba,\nEmi ‘bukun wa, mo n daku\nMu mi re‘bi ‘sinmi."
            },
            {
                "stanza": "2",
                "lyric": "Mo fi duru mi kọ,\nS’ori igi wilo;\nN o se kọrin ayọ, gbati\n‘Wọ ko i t’ahọn mi se?"
            },
            {
                "stanza": "3",
                "lyric": "Ẹmi mi lọ sile,\nA! mba le fo de ‘bẹ,\nAyun rẹ n yun mi wọ Sioni,\nGba mo ba ranti rẹ."
            },
            {
                "stanza": "4",
                "lyric": "Sọdọ rẹ mo n t’ọna,\nT’o kun fun isoro;\n‘Gbawo ni n o kọj’ aginju,\nDe ‘lẹ awọn mimọ?"
            },
            {
                "stanza": "5",
                "lyric": "Sunmọ mi, Ọlọrun,\n‘Wọ ni mo gbẹkẹle;\nSin mi la aginju aye;\nKi n de‘le nikẹhin.\nAMIN."
            }
        ],
        "song_tag": "(FE266)"
    },
    {
        "no": 247,
        "heading": "C.M.S. 150 t.H.C. 164 tabi H.C. 140 C.M.",
        "sub_heading": "Enyin pelu nfe lo bi?",
        "bible_verse": "- John 6 : 67.",
        "intro": "",
        "title": "NIGBA wọn kẹhin si Sioni,",
        "category": "ORIN IRONUPIWADA",
        "tune": "",
        "lyrics": [
            {
                "stanza": "1",
                "lyric": "NIGBA wọn kẹhin si Sioni,\nA! ọpọ n’iye wọn;\nMo sẹ b’Olugbala wi pe,\n‘Wọ fẹ kọ mi pẹlu?"
            },
            {
                "stanza": "2",
                "lyric": "T’emi t’ọkan b’iru eyi,\nA fi b’O di mi mu;\nN ko le se ki n ma fa sẹhin,\nK’emi si dabi wọn."
            },
            {
                "stanza": "3",
                "lyric": "Mo mọ, Iwọ l’o l’agbara,\nLati gba otosi;\nOdọ tani emi o lọ?\nBi mo kẹhin si Ọ?"
            },
            {
                "stanza": "4",
                "lyric": "O da mi loju papa pe,\nIwọ ni Kristi na!\nẸni t'o ni ẹmi iye,\nNipa ti ẹjẹ Rẹ."
            },
            {
                "stanza": "5",
                "lyric": "Ohun Rẹ f'isinmi fun mi,\nO si l'ẹru mi lọ;\nIfẹ Rẹ lo le mu mi yọ,\nO si to f'ọkan mi."
            },
            {
                "stanza": "6",
                "lyric": "Bi 'bere yi ti dun mi to,\nPe emi o lọ bi?\"\nOluwa, ni 'gbẹkẹle Rẹ,\nMo dahun pe \"Bẹkọ\".\nAMIN."
            }
        ],
        "song_tag": "(FE267)"
    },
    {
        "no": 248,
        "heading": "t.H.C. 133 C.M.",
        "sub_heading": "Omokunrin tujuka, a dari ese re ji o",
        "bible_verse": "- Matt. 9 : 2.",
        "intro": "",
        "title": "Jesu mi, mu mi gb' ohun Rẹ",
        "category": "ORIN IRONUPIWADA",
        "tune": "",
        "lyrics": [
            {
                "stanza": "1",
                "lyric": "Jesu mi, mu mi gb' ohun Rẹ\nS'ọrọ alafia;\nGbogbo ipa mi y'o dalu\nLati yin ore Rẹ."
            },
            {
                "stanza": "2",
                "lyric": "Fi iyọnu pe mi l'ọmọ,\nK'o si dariji mi;\nOhun na yoo dun mọ mi,\nB'iro orin ọrun."
            },
            {
                "stanza": "3",
                "lyric": "Ibikibi t'o tọ mi si,\nL'emi o f'ayọ lọ;\nTayọtayọ l'emi o si\nDapọ m'awọn oku."
            },
            {
                "stanza": "4",
                "lyric": "'Gba ẹru ẹbi ba kọja,\nẸru mi ko si mọ,\nỌwọ t'o fun 'dariji ka,\nY' o pin ade iye.\nAMIN."
            }
        ],
        "song_tag": "(FE269)"
    },
    {
        "no": 249,
        "heading": "C.M.S. 154 H.C. 323, C.M.",
        "sub_heading": "Awa ko ni Olori Alufa ti o se alaimo eedun ailera wa.",
        "bible_verse": "- Heb. 4 : 15.",
        "intro": "",
        "title": "A F'AYỌ r'ore-ọfẹ",
        "category": "ORIN IRONUPIWADA",
        "tune": "",
        "lyrics": [
            {
                "stanza": "1",
                "lyric": "A F'AYỌ r'ore-ọfẹ\nT' Alufa giga wa,\nỌkan Rẹ kun fun iyọnu,\nInu Rẹ n yọ fun 'fẹ."
            },
            {
                "stanza": "2",
                "lyric": "Tinutinu l'o n daro wa,\nO mọ ailera wa;\nO mọ bi idanwo ti ri,\nNitori O ti ri."
            },
            {
                "stanza": "3",
                "lyric": "On papa l'ọjọ aye Rẹ,\nO sọkun kikoro;\nO mba olukuluku pin,\nNinu iya ti n jẹ."
            },
            {
                "stanza": "4",
                "lyric": "Je ki a f'igbagbọ 'rẹlẹ,\nW'anu at'ipa Rẹ,\nAwa o si ri igbala,\nL'akoko iyọnu.\nAMIN."
            }
        ],
        "song_tag": "(FE269)"
    },
    {
        "no": 250,
        "heading": "C.M.S. 145 H.C. 145 7s.",
        "sub_heading": "Ranti, Oluwa",
        "bible_verse": "- Ps. 106 : 4",
        "intro": "",
        "title": "JESU jọ ranti mi,",
        "category": "ORIN IRONUPIWADA",
        "tune": "",
        "lyrics": [
            {
                "stanza": "1",
                "lyric": "JESU jọ ranti mi,\nK'O si w'ẹsẹ mi nu;\nGba mi lọw' ẹsẹ 'binibi,\nSi wẹ ọkan mi mọ."
            },
            {
                "stanza": "2",
                "lyric": "Jesu, jọ ranti mi,\nEm' ẹni 'nilara;\nKi m'se 'ransẹ t'o n'ifẹ Rẹ\nKi m'tọ 'sinmi Rẹ wo."
            },
            {
                "stanza": "3",
                "lyric": "Jesu, jọ ranti mi,\nMase jẹ ki n sako;\nN'nu 'damu oun okun aye,\nF'ọna ọrun han mi."
            },
            {
                "stanza": "4",
                "lyric": "Jesu, jọ ranti mi,\nGba gbogbo rẹ kọja,\nKi n le r'ogo ainipẹkun,\nKi n si le ba Ọ yọ"
            },
            {
                "stanza": "5",
                "lyric": "Jesu jọ ranti mi,\nKi n le kọrin loke;\nSi Baba, mi ati Rẹ,\nOrin 'yin at' ifẹ.\nAmin."
            }
        ],
        "song_tag": "(FE270)"
    },
    {
        "no": 251,
        "heading": "C.M.S. 157 H.C. 162 L.M.",
        "sub_heading": "Nigbana ni o sanu fun, o si wipe Gba kuro ninu lilo sinu iho, emi ti ri irapada!",
        "bible_verse": "- John 33:24.",
        "intro": "",
        "title": "Bi mo ti kunlẹ, Oluwa,",
        "category": "ORIN IRONUPIWADA",
        "tune": "",
        "lyrics": [
            {
                "stanza": "1",
                "lyric": "Bi mo ti kunlẹ, Oluwa,\nTi mo mbẹ f' anu lọdọ Rẹ,\nWọ t'Ọrẹ lẹsẹ ti n ku lọ,\nSi 'tori Rẹ gb' adura mi."
            },
            {
                "stanza": "2",
                "lyric": "Ma ro 'tiju at' ẹbi mi,\nAt' aimoye abawọn mi,\nRo t'ẹjẹ ti Jesu ta 'lẹ,\nFun 'dariji oun iye mi."
            },
            {
                "stanza": "3",
                "lyric": "Ranti bi mo ti jẹ Tirẹ,\nTi mo jẹ ẹda ọwọ Rẹ;\nRo b'ọkan mi ti fa s'ẹsẹ,\nBi 'danwo si ti yi mi ka."
            },
            {
                "stanza": "4",
                "lyric": "A! ronu ọrọ mimọ Rẹ,\nAti gbogbo ileri Rẹ;\nPe 'Wọ o gbọ adua titi,\nOgo Rẹ ni lati dasi."
            },
            {
                "stanza": "5",
                "lyric": "A! ma ro ti 'yemeji mi,\nAti ailo or'-ọfẹ Rẹ;\nRo ti omije Jesu mi,\nSi fi 'toye Rẹ di temi."
            },
            {
                "stanza": "6",
                "lyric": "Oju oun eti Rẹ ko se,\nAgbara Rẹ ko le yẹ lai;\nJọ wo mi: ọkan mi wuwo,\nDa mi si, k'O ran mi lọwọ.\nAMIN."
            }
        ],
        "song_tag": "(FE271)"
    },
    {
        "no": 252,
        "heading": "C.M.S. 159 t.H.C. 156 L.M.",
        "sub_heading": "Oluwa, kiyesi aroye mi",
        "bible_verse": "- Ps. 5:1.",
        "intro": "",
        "title": "Bi mo ti kunlẹ, Oluwa,",
        "category": "ORIN IRONUPIWADA",
        "tune": "",
        "lyrics": [
            {
                "stanza": "1",
                "lyric": "OLUWA, gbọ aroye mi;\nGbọ adura ikọkọ mi,\nLọdọ Rẹ nikan, Ọba mi,\nL'emi o ma wa iranwọ"
            },
            {
                "stanza": "2",
                "lyric": "L'orọ Iwọ o gbohun mi,\nL' afẹmọjumọ ọjọ na,\nNi ọdọ Rẹ l'emi o wọ;\nSi Ọ l'emi o gbadura."
            },
            {
                "stanza": "3",
                "lyric": "Sugbọn nigb' ore-ọfẹ Rẹ,\nBa mu mi de agbala Rẹ;\nỌdọ Rẹ l'emi o tẹju mọ,\nNibẹ, n o sin Ọ ni rẹlẹ."
            },
            {
                "stanza": "4",
                "lyric": "Jẹ k'awọn t'o gbẹkẹlẹ Ọ,\nL'ohun rara wi ayọ wọn;\nJẹ k'awọn t'Iwọ pamọ yọ,\nAwọn t'o fẹ orukọ Rẹ."
            },
            {
                "stanza": "5",
                "lyric": "Si Olododo l'Oluwa,\nO na ọwọ ibukun Rẹ;\nOju rere Re l'eniyan Rẹ,\nYoo si fi se asa wọn.\nAMIN."
            }
        ],
        "song_tag": "(FE272)"
    },
    {
        "no": 253,
        "heading": "C.M.S. 160 H.C. 548 C.M.",
        "sub_heading": "Gba mi la nitori anu Re",
        "bible_verse": "- Ps. 6:4.",
        "intro": "",
        "title": "BABA, ma yi oju kuro,",
        "category": "ORIN IRONUPIWADA",
        "tune": "",
        "lyrics": [
            {
                "stanza": "1",
                "lyric": "BABA, ma yi oju kuro,\nFun emi otosi;\nTi n ponhunrere ẹsẹ mi,\nN' iwaju itẹ Rẹ."
            },
            {
                "stanza": "2",
                "lyric": "'Lẹkun aanu to si silẹ,\nF'akerora ẹsẹ,\nMase ti mọ mi Oluwa,\nJẹ ki emi wọle."
            },
            {
                "stanza": "3",
                "lyric": "Emi ko ni pe mo n jẹwọ,\nB'aye mi ti ri ri;\nGbogbo rẹ lat' ẹhin wa, ni\n'Wọ mọ dajudaju."
            },
            {
                "stanza": "4",
                "lyric": "Mo wa si 'lẹkun anu Rẹ\nNibi ti anu pọ:\nMo fẹ 'dariji ẹsẹ mi,\nK'O mu ọkan mi da."
            },
            {
                "stanza": "5",
                "lyric": "Emi ko ni ma tẹnumọ,\nItunu ti mo n fẹ;\n'Wọ mọ, Baba, ki n to bere,\nIbukun t'emi n wa."
            },
            {
                "stanza": "6",
                "lyric": "Anu, Oluwa, ni mo fẹ,\nEyi yii l'opin na;\nOluwa, anu l'o yẹ mi,\nJẹ ki anu Rẹ wa.\nAMIN."
            }
        ],
        "song_tag": "(FE273)"
    },
    {
        "no": 254,
        "heading": "C.M.S. 161 K. 523 t.H.C. 17 L.M.",
        "sub_heading": "Abo mi mbe lodo Olorun.",
        "bible_verse": "- Ps. 7:10.",
        "intro": "",
        "title": "Pẹlu mi nibi ti mo n lọ,",
        "category": "ORIN IRONUPIWADA",
        "tune": "C.M.S. 161 K. 523 t.H.C. 17 L.M.",
        "lyrics": [
            {
                "stanza": "1",
                "lyric": "Pẹlu mi nibi ti mo n lọ,\nKọ mi l'ohun t'emi o se;\nSa gbọ aro at'ọrọ mi,\nK'o f'ẹsẹ mi le ọna Rẹ."
            },
            {
                "stanza": "2",
                "lyric": "Fi ọpọ ifẹ Rẹ fun mi,\nMa se alabo mi lailai;\nFi edidi Rẹ s'aya mi,\nJẹ ki Ẹmi Rẹ pẹlu mi."
            },
            {
                "stanza": "3",
                "lyric": "Ko mi bi a ti gbadura,\nJẹ ki emi gba Iwọ gbọ;\nKi n korira nkan t'O ko fẹ,\nK'emi si fẹ 'hun ti O fẹ.\nAMIN."
            }
        ],
        "song_tag": "(FE274)"
    },
    {
        "no": 255,
        "heading": "C.M.S. 163 t.H.C. 152 C.M.",
        "sub_heading": "OLorun sanu fun mi, elese",
        "bible_verse": "- Luku 18:13.",
        "intro": "",
        "title": "OLUWA, b'agbowode ni",
        "category": "ORIN IRONUPIWADA",
        "tune": "",
        "lyrics": [
            {
                "stanza": "1",
                "lyric": "OLUWA, b'agbowode ni\nMo gb'ọkan mi le Ọ;\nOluwa, f'ore-ọfẹ wi,\nK'o se anu fun mi."
            },
            {
                "stanza": "2",
                "lyric": "Mo lu aiduro aya mi,\nẸkun at' irora;\nK'o gb'ọkan mi nu irora,\nK'o se anu fun mi."
            },
            {
                "stanza": "3",
                "lyric": "N' itiju mo jẹw' ẹsẹ mi,\nJọ fun mi ni ireti,\nMo bẹ, 'tori ẹjẹ Jesu,\nK'O se anu fun mi."
            },
            {
                "stanza": "4",
                "lyric": "Olori ẹlẹsẹ ni mi,\nẸsẹ mi p'apọju:\nNitori iku Jesu wa,\nK'O se anu fun mi.\n"
            },
            {
                "stanza": "5",
                "lyric": "Mo duro ti agbelebu,\nNko sa f'ojiji rẹ;\nTi Ọlọrun to pọ l' anu,\nO ti sanu fun mi.\n"
            }
        ],
        "song_tag": "(FE275)"
    },
    {
        "no": 256,
        "heading": "C.M.S. 172 H.C. 159 8s. 6.",
        "sub_heading": "Enikeni ti o to mi wa, emi ki yio ta nu bi o ti wu ki ori",
        "bible_verse": "- John 6 : 37.",
        "intro": "",
        "title": "Bi mo ti ri: laisawawi,",
        "category": "ORIN IRONUPIWADA",
        "tune": "",
        "lyrics": [
            {
                "stanza": "1",
                "lyric": "Bi mo ti ri: laisawawi,\nSugbọn nitori ẹjẹ Rẹ,\nB'O si ti pe mi pe ki n wa,\nOlugbala, mo de."
            },
            {
                "stanza": "2",
                "lyric": "Bi mo ti ri: laiduro pẹ,\nMo fẹ k'ọkan mi mọ toto,\nSọdọ Rẹ t'o le wẹ mi mọ,\nOlugbala, mo de."
            },
            {
                "stanza": "3",
                "lyric": "Bi mo ti ri, b'o tilẹ jẹ,\nIja lode, ija ninu:\nẸru lode, ẹru ninu,\nOlugbala mo de."
            },
            {
                "stanza": "4",
                "lyric": "Bi mo ti ri: osi, are,\nMo si n wa, imularada;\nIwọ lo le s'awotan mi,\nOlugbala, mo de."
            },
            {
                "stanza": "5",
                "lyric": "Bi mo ti ri: 'Wọ o gba mi,\n'Wọ o gba mi tọwọ-tẹsẹ,\n'Tori mo gba 'leri Rẹ gbọ,\nOlugbala, mo de."
            },
            {
                "stanza": "6",
                "lyric": "Bi mo ti ri: Ifẹ Tirẹ,\nLo sẹtẹ mi patapata;\nMo di Tirẹ, Tirẹ nikan,\nOlugbala, mo de.\nAMIN."
            }
        ],
        "song_tag": "(FE276)"
    },
    {
        "no": 257,
        "heading": "C.M.S. 173 H.C. 160 D. 6s. 5s.",
        "sub_heading": "Mo ti gbadura fun o, ki igbagbo re mase ye",
        "bible_verse": "- Luku 22 : 32.",
        "intro": "",
        "title": "JESU, nigba 'danwo,",
        "category": "ORIN IRONUPIWADA",
        "tune": "",
        "lyrics": [
            {
                "stanza": "1",
                "lyric": "JESU, nigba 'danwo,\nGbadura fun mi,\nK' emi ma ba sẹ Ọ,\nKi n si sako lọ;\n'Gba mba siyemeji,\nK'O bojuwo mi;\nK' ẹru tab' isaju.\nMa mu mi subu."
            },
            {
                "stanza": "2",
                "lyric": "B'aye ba si n fa mi,\nPẹlu adun rẹ;\nT' Ohun 'sura aye,\nFẹ han mi l'emọ;\nJọ mu Gatsemane,\nWa s'iranti mi,\nTabi irora Rẹ,\nLoke Kalfari."
            },
            {
                "stanza": "3",
                "lyric": "B'O ba pọn mi loju,\nNinu ifẹ Rẹ;\nDa ibukun Rẹ le;\nOri ẹbọ na:\nKi n f'ara mi fun Ọ,\nLori pẹpẹ Rẹ;\nB'ara kọ ago na\nIgbagbọ y'o mu."
            },
            {
                "stanza": "4",
                "lyric": "'Gba mo ba n re 'boji,\nSinu ekuru;\nT'ogo ọrun si n kọ,\nLeti bebe na;\nN o gbẹkẹl' ootọ Rẹ,\nN' ijakadi 'ku;\nOluwa, gb'ẹmi mi,\nS' iye ailopin.\nAMIN."
            }
        ],
        "song_tag": "(FE277)"
    },
    {
        "no": 258,
        "heading": "C.M.S. 173 H.C. 163 D. 7s. 6s.",
        "sub_heading": "Eni itewogba ninu Ayanfe",
        "bible_verse": "- Efe. 1 : 6",
        "intro": "",
        "title": "MO Kẹsẹ mi le, Jesu,",
        "category": "ORIN IRONUPIWADA",
        "tune": "",
        "lyrics": [
            {
                "stanza": "1",
                "lyric": "MO Kẹsẹ mi le, Jesu,\nỌd' aguntan Mimọ;\nO ru gbogbo ẹru mi,\nO sọ mi d'ominira;\nMo ru ẹbi mi tọ wa,\nK'o wẹ eeri mi nu,\nK'ẹjẹ Rẹ iyebiye,\nLe sọ mi di funfun."
            },
            {
                "stanza": "2",
                "lyric": "Mo k'aini mi le Jesu,\nTirẹ l'ohun gbogbo;\nO w'arun mi gbogbo san,\nO r'ẹmi mi pada;\nMo ko ibanujẹ mi,\nẸru at' aniyan\nLe Jesu, O si gba mi,\nO gba irora mi."
            },
            {
                "stanza": "3",
                "lyric": "Mo gb'ọkan mi le Jesu,\nỌkan arẹ mi yii;\nỌw' ọtun Rẹ gba mi mu,\nMo sinmi laya Rẹ;\nMo fẹ orukọ Jesu,\nEmmanuẹl, Kristi;\nBi orun didun yika,\nNi orukọ Rẹ jẹ."
            },
            {
                "stanza": "4",
                "lyric": "Mo fẹ ki n ri bi Jesu,\nT'ọkan Rẹ kun fun 'fẹ;\nMo fẹ ki n ri bi Jesu,\nỌmọ Mimọ Baba;\nMo fẹ ki mba Jesu gbe,\nLarin ẹgbẹ mimọ;\nKi n kọrin iyin titi,\nOrin t'Angẹli n kọ.\nAMIN."
            }
        ],
        "song_tag": "(FE278)"
    },
    {
        "no": 259,
        "heading": "C.M.S. 175, H.C. 169 7s. 6s. 11",
        "sub_heading": "Enikeni ti o ba si fe, ki o gba omi iye na lofe",
        "bible_verse": "- Efe. 1 : 6",
        "intro": "",
        "title": "OTOSI ẹlẹsẹ, ẹ wa,",
        "category": "ORIN IRONUPIWADA",
        "tune": "",
        "lyrics": [
            {
                "stanza": "1",
                "lyric": "OTOSI ẹlẹsẹ, ẹ wa,\nWa ni wakati anu;\nJesu setan lati gba yin,\nO kun f'anu at'ifẹ,\nO si le sẹ, O mura tan, ma foya."
            },
            {
                "stanza": "2",
                "lyric": "Ẹyin alaini, ẹ wa gba\nOgo Ọlọrun l'ofẹ,\n'Gbagbọ totọ, 'ronu totọ,\nOr' ọfẹ ti o n fa wa,\nWa 'dọ Jesu, alaini owo sa wa ra."
            },
            {
                "stanza": "3",
                "lyric": "Ma jẹ k'ọkan yin da yin ro\nMase ro ti aiyẹ yin;\nGbogbo yiyẹ t'o mbere ni,\nKi ẹ sa mọ aini yin,\n'Yi l'O fun yin; 'tansan\nẸmi l'ọkan."
            },
            {
                "stanza": "4",
                "lyric": "Ẹyin t'ẹru n pa, t'aarẹ mu,\nT'ẹ sọnu t'ẹ si segbe,\nBi ẹ duro tit' ẹ o fi san,\nẸ ki yoo wa rara:\nF'ẹlẹsẹ ni, Oun ko wa f'olododo."
            },
            {
                "stanza": "5",
                "lyric": "Ọlọrun goke l'awọ wa,\nO n fi ẹjẹ Rẹ bẹbẹ:\nGbe ara le patapata:\nMa gbẹkẹle ohun mi?\nJesu nikan l'o le s'ẹlẹsẹ l'ore."
            },
            {
                "stanza": "6",
                "lyric": "Angẹli at' awọn mimọ,\nN kọrin 'yin Ọd'-agutan;\nGbohungbohun Orukọ Rẹ,\nSi gba gbogbo ọrun kan:\nHalleluya! ẹlẹsẹ le gberin na.\nAMIN."
            }
        ],
        "song_tag": "(FE279)"
    },
    {
        "no": 260,
        "heading": "C.M.S. 176, H.C. 170 D 7s.",
        "sub_heading": "Nitori kini enyin o se ku, ile Israel.",
        "bible_verse": "- Ex. 33 : 11",
        "intro": "",
        "title": "Ẹlẹsẹ, ẹ yi pada,",
        "category": "ORIN IRONUPIWADA",
        "tune": "",
        "lyrics": [
            {
                "stanza": "1",
                "lyric": "Ẹlẹsẹ, ẹ yi pada,\nEese ti ẹ o fi ku?\nẸlẹda yin lo n bere?\nT'o fẹ ki ẹ ba Oun gbe,\nỌran nla ni O mbi yin,\nIsẹ ọwọ Rẹ ni yin,\nA! ẹyin alailọpẹ,\nEese t'ẹ o ko 'fẹ Rẹ."
            },
            {
                "stanza": "2",
                "lyric": "Ẹlẹsẹ, ẹ yi pada,\nEese ti ẹ fi ku?\nOlugbala ni n bere,\nẸni t'o gb'ẹmi yin la;\nIku Rẹ y'o j'asan bi?\nẸ o tun kan mọ 'gi bi?\nẸni 'rapada, eese\nTi ẹ o gan ore Rẹ?"
            },
            {
                "stanza": "3",
                "lyric": "Ẹlẹsẹ, ẹ yi pada,\nEese ti ẹ o fi ku?\nẸmi Mimọ ni n bere,\nTi n f'ọjọ gbogbo rọ yin,\nẸ ki o ha gb'ọrọ Rẹ?\nẸ o ko iye silẹ?\nA ti n wa yin pẹ, eese,\nT'ẹ n bi Ọlọrun ninu?"
            },
            {
                "stanza": "4",
                "lyric": "Iyemeji ha n se yin,\nPe Ifẹ ni Ọlọrun?\nẸ ki o ha gb'ọrọ Rẹ,\nK' ẹ gba ileri rẹ gbọ?\nW'Oluwa yin; lọdọ yin,\nJesu n sun; w'omije Rẹ,\nẸjẹ Rẹ pẹlu n ke, pe,\nEese ti ẹ o fi ku\nAMIN."
            }
        ],
        "song_tag": "(FE280)"
    },
    {
        "no": 261,
        "heading": "C.M.S. 177 H.C. 305 11s.",
        "sub_heading": "On le pa eyiti mo fi le le lowo mo",
        "bible_verse": "- II Tim. 1:12",
        "intro": "",
        "title": "",
        "category": "ORIN IRONUPIWADA",
        "tune": "JESU, emi o fi ọkan mi fun Ọ,",
        "lyrics": [
            {
                "stanza": "1",
                "lyric": "JESU, emi o fi ọkan mi fun Ọ,\nMo jẹbi, mo gbe, sugbọn\n'Wọ le gba mi;\nL'aye ati l'ọrun, ko sẹni bi Rẹ,\n Iwọ ku f'ẹlẹsẹ - f'emi na pẹlu."
            },
            {
                "stanza": "2",
                "lyric": "Jesu, mo le sinmi le orukọ Rẹ,\nTi Angeli wa sọ, l'ọjọ ibi Rẹ,\n'Yi t'a kọ ti o han lor' agbelebu,\nTi ẹlẹsẹ si ka; wọn si tẹriba."
            },
            {
                "stanza": "3",
                "lyric": "Jesu, emi ko le saigbẹkẹle Ọ,\nIsẹ Rẹ l'aye kun f'anu at' ifẹ,\nẸlẹsẹ yi Ọ ka, adẹtẹ ri Ọ,\nKo s'ẹni buruju, t'Iwọ ko le gba."
            },
            {
                "stanza": "4",
                "lyric": "Jesu mo le gbẹkẹ mi le ọrọ Rẹ,\nBi n o tilẹ gbọ ohun anu Rẹ ri;\nGbat' Ẹmi Rẹ n tọ ni, o ti dun pọ to,\nKi n sa f'ibaralẹ k'ẹkọ lẹsẹ Rẹ."
            },
            {
                "stanza": "5",
                "lyric": "Jesu totọ-totọ, mo gbẹkẹle Ọ,\nẸnikẹni t'o wa, Wọ ki o ta nu;\nOotọ ni 'leri Rẹ, ọwọn l'ẹjẹ Rẹ:\n'Wọnyi n'igbala mi, 'Wọ l'Ọlọrun mi.\nAMIN"
            }
        ],
        "song_tag": "(FE281)"
    },
    {
        "no": 262,
        "heading": "C.M.S. 188 H.C. 173 L.M.",
        "sub_heading": "E tetilele, ki e si wa si odo mi, e gbo, okan nyin o si ye",
        "bible_verse": "- Isa. 53:3",
        "intro": "",
        "title": "ỌLỌRUN, Baba mi, 'Wọ n pe,",
        "category": "ORIN IRONUPIWADA",
        "tune": "",
        "lyrics": [
            {
                "stanza": "1",
                "lyric": "ỌLỌRUN, Baba mi, 'Wọ n pe,\nAsako ọmọ Rẹ mọra?\nIwọ o ha dariji mi?\nMo de, mo de, jọ gba mi la."
            },
            {
                "stanza": "2",
                "lyric": "A! Jesu, Iwọ n rekọja,\nPẹlu ore at' agbara?\n'Wọ ko ha n gbọ igbe mi bi?\nMo de, mo de, saanu fun mi."
            },
            {
                "stanza": "3",
                "lyric": "A! Ẹmi Mimọ Iwọ ni?\nỌrẹ ti mo ti sati pẹ!\n'Wọ ha n bẹbẹ fun mi sibẹ?\nMo de, mo de, m'ailera le."
            },
            {
                "stanza": "4",
                "lyric": "Mo de, Oluwa, ifẹ Rẹ,\nNi o n rọ mi t'o si n fa mi:\nMo wolẹ lẹsẹ rẹ, ki n mọ,\nB'o ti dun lati jẹ Tirẹ.\nAMIN"
            }
        ],
        "song_tag": "(FE282)"
    },
    {
        "no": 263,
        "heading": "H.C. 171 8s. 6s. 4.",
        "sub_heading": "Israeli, yipada si Oluwa Olorun re",
        "bible_verse": "- Hos. 14:1",
        "intro": "",
        "title": "Pada asako, s'ile rẹ,",
        "category": "ORIN IRONUPIWADA",
        "tune": "",
        "lyrics": [
            {
                "stanza": "1",
                "lyric": "Pada asako, s'ile rẹ,\nBaba rẹ l'o n pe ọ;\nMase alarinkiri mọ,\nNin' ẹsẹ at'osi;\nPada, pada."
            },
            {
                "stanza": "2",
                "lyric": "Pada asako s'ile rẹ,\nJesu l'o sa n pe ọ;\nẸmi pẹlu Ijọ si n pe,\nYara sa asala;\nPada, pada."
            },
            {
                "stanza": "3",
                "lyric": "Pada asako s'ile rẹ,\nWere ni, b'o ba pẹ;\nKo si 'dariji n'iboji,\nỌjọ anu kuru;\nPada, pada.\nAMIN"
            }
        ],
        "song_tag": "(FE283)"
    },
    {
        "no": 264,
        "heading": "H.C. 176 D. 7s.",
        "sub_heading": "Emi o ha se jowo re lowo",
        "bible_verse": "- Hos. 11:8",
        "intro": "",
        "title": "Ibu anu! O le jẹ",
        "category": "ORIN IRONUPIWADA",
        "tune": "",
        "lyrics": [
            {
                "stanza": "1",
                "lyric": "Ibu anu! O le jẹ\nP'anu si mbẹ fun mi?\nỌlọrun le mu suru,\nF'emi olori ẹlẹsẹ?\nMo ti kọ or'-ọfẹ Rẹ,\nMo bi n'nu lojukoju;\nN ko f'eti si ipe Rẹ;\nMo sọ ninu l'ainiye."
            },
            {
                "stanza": "2",
                "lyric": "Mo tan an ni suru to;\nSibẹ o si da mi si;\nO n ke, \"N o se jọwọ rẹ!\nSa gba ago igbala,\nOlugbala mi n duro,\nO si n fi ọgbẹ Rẹ han,\nMo mọ, ifẹ l'Ọlọrun;\nJesu, n sun, O fẹran mi."
            },
            {
                "stanza": "3",
                "lyric": "Jesu, dahun lat' oke;\nIfẹ k'iwa Rẹ gbogbo?\n'Wọ ki y'o dariji mi,\nKi n wolẹ ni ẹsẹ Rẹ?\nBi 'm' ba mọ inu Rẹ re,\nB' Iwọ 'ba se alanu,\nF'anu dẹti Rẹ silẹ,\nDariji, k'a si gba mi."
            },
            {
                "stanza": "4",
                "lyric": "F'oju iyọnu wo mi,\nFi wuwo oju pe mi,\nMu ọkan okuta rọ,\nYipada, rọ mi lọkan,\nMu mi ronupiwada;\nJẹ ki n gbawẹ f'ẹsẹ mi;\nKi n si kaanu isẹ mi,\nKi n gbagbọ, ki n ye dẹsẹ.\nAMIN"
            }
        ],
        "song_tag": "(FE284)"
    },
    {
        "no": 265,
        "heading": "H.C. 172 t.S. 56 8s. 7s. 3",
        "sub_heading": "Ojo ibukun o si ro",
        "bible_verse": "- Esek. 34:25",
        "intro": "",
        "title": "Oluwa mo gbọ pe, Iwọ,",
        "category": "ORIN IRONUPIWADA",
        "tune": "",
        "lyrics": [
            {
                "stanza": "1",
                "lyric": "Oluwa mo gbọ pe, Iwọ,\nNrọ ojo 'bukun kiri;\nItunu fun ọkan arẹ,\nRọ ojo naa sori mi \n",
                "Egbe": "An' emi, an' emi,\nRọ ojo naa sori mi.\n"
            },
            {
                "stanza": "2",
                "lyric": "Ma kọja, Baba Olore,\nBi ẹsẹ mi tilẹ pọ;\n'Wọ le fi mi silẹ, sugbọn\nJẹ k'anu rẹ ba le mi\n",
                "Egbe": "An' emi, an' emi,\nJẹ k'anu rẹ ba le mi.\n"
            },
            {
                "stanza": "3",
                "lyric": "Ma kọja mi, Olugbala,\nJẹ k' emi le rọ mọ ọ,\nEmi n wa oju rere Rẹ,\nPe mi mọ awọn t'o n pe \n",
                "Egbe": "An' emi, an' emi,\nPe mi mọ awọn t'o n pe\n"
            },
            {
                "stanza": "4",
                "lyric": "Ma kọja mi, Ẹmi Mimọ,\n'Wọ le la 'ju afọju;\nẸlẹri itoye Jesu,\nSọrọ asẹ naa si mi\n",
                "Egbe": "An' emi, an' emi,\nSọrọ asẹ naa si mi.\n"
            },
            {
                "stanza": "5",
                "lyric": "Mo ti sun fọnfọn nin' ẹsẹ,\nMo bi Ọ ninu kọja;\nAye ti de ọkan mi jọ,\nTu mi k'o dariji mi\n",
                "Egbe": "An' emi, an' emi,\nTu mi k'o dariji mi.\n"
            },
            {
                "stanza": "6",
                "lyric": "Ifẹ Ọlọrun ti ki yẹ,\nẸjẹ Krist' iyebiye,\nOre-ọfẹ alainiwọn;\nGbe gbogbo rẹ ga n'nu mi\n",
                "Egbe": "An' emi, an' emi,\nGbe gbogbo rẹ ga n'nu mi\n"
            },
            {
                "stanza": "7",
                "lyric": "Ma kọja mi dariji mi,\nFa mi mọra, Oluwa;\n'Gba o n f'ibukun f'ẹlomi,\nMasai f'ibukun fun mi\n",
                "Egbe": "An' emi, an' emi,\nMasai f'ibukun fun mi\nAMIN."
            }
        ],
        "song_tag": "(FE285)"
    },
    {
        "no": 266,
        "heading": "S. 124 t.H.C 336 11s.",
        "sub_heading": "Ikilo meta :- Ma ba ja, ma bi ninu, ma pa ina Emi",
        "bible_verse": "",
        "intro": "",
        "title": "Iwọ ẹlẹsẹ, Emi n fi anu pe",
        "category": "ORIN IRONUPIWADA",
        "tune": "",
        "lyrics": [
            {
                "stanza": "1",
                "lyric": "Iwọ ẹlẹsẹ, Emi n fi anu pe\nỌkan rẹ t'o ti yigbi ninu ẹsẹ;\nMa se ba Emi ja, ma pẹ titi mọ,\nẸbẹ Ọlọrun rẹ le pari loni."
            },
            {
                "stanza": "2",
                "lyric": "Ọmọ Ijọba, mas' ẹru ẹsẹ mọ;\nGb' ẹbun Ẹmi Mimọ ati itunu;\nMa bi Ẹmi ninu, Olukọ rẹ ni-\nK'a ba le se Olugbala rẹ logo."
            },
            {
                "stanza": "3",
                "lyric": "Tẹmpili d'ibajẹ, ẹwa rẹ d'ile\nIna pẹpẹ Ọlọrun fẹrẹ ku tan,\nBi a fi ifẹ da, O si le tun ran:\nMase pa 'na Ẹmi, Oluwa mbọ wa.\nAMIN."
            }
        ],
        "song_tag": "(FE286)"
    },
    {
        "no": 267,
        "heading": "C.M.",
        "sub_heading": "Oju OLuwa mbe nibi gbogbo",
        "bible_verse": "- Owe 15 : 3.",
        "intro": "",
        "title": "Isẹ gbogbo ti awa n se",
        "category": "ORIN IRONUPIWADA",
        "tune": "",
        "lyrics": [
            {
                "stanza": "1",
                "lyric": "Isẹ gbogbo ti awa n se,\nNi Ọlọrun ti ri;\nEro gbogbo t'o wa ninu,\nNi Ọlọrun si mọ."
            },
            {
                "stanza": "2",
                "lyric": "A ko le f'ẹsẹ wa pamọ,\nGbogbo wọn l'O ti mọ;\nA n purọ, a n tan 'ra wa jẹ,\nB'a ro pe ko mọ wọn."
            },
            {
                "stanza": "3",
                "lyric": "Ohun gbogbo han ni gbangban,\nNi oju Ọlọrun;\nOkunkun ati imọlẹ,\nSi ri bakan naa fun."
            },
            {
                "stanza": "4",
                "lyric": "Ọlọrun, jẹ k'a ranti pe,\nOju rẹ si ri wa;\nSi jẹ ki awa k'o bẹru,\nLati dẹsẹ si Ọ.\n"
            }
        ],
        "song_tag": "(FE287)"
    },
    {
        "no": 267,
        "heading": "C.M.",
        "sub_heading": "Oju OLuwa mbe nibi gbogbo",
        "bible_verse": "- Owe 15 : 3.",
        "intro": "",
        "title": "Isẹ gbogbo ti awa n se",
        "category": "ORIN IRONUPIWADA",
        "tune": "",
        "lyrics": [
            {
                "stanza": "1",
                "lyric": "Isẹ gbogbo ti awa n se,\nNi Ọlọrun ti ri;\nEro gbogbo t'o wa ninu,\nNi Ọlọrun si mọ."
            },
            {
                "stanza": "2",
                "lyric": "A ko le f'ẹsẹ wa pamọ,\nGbogbo wọn l'O ti mọ;\nA n purọ, a n tan 'ra wa jẹ,\nB'a ro pe ko mọ wọn."
            },
            {
                "stanza": "3",
                "lyric": "Ohun gbogbo han ni gbangban,\nNi oju Ọlọrun;\nOkunkun ati imọlẹ,\nSi ri bakan naa fun."
            },
            {
                "stanza": "4",
                "lyric": "Ọlọrun, jẹ k'a ranti pe,\nOju rẹ si ri wa;\nSi jẹ ki awa k'o bẹru,\nLati dẹsẹ si Ọ.\n"
            }
        ],
        "song_tag": "(FE287)"
    },
    {
        "no": 268,
        "heading": "",
        "sub_heading": "A dari ese re ji o",
        "bible_verse": "- Luku 5 : 20.",
        "intro": "",
        "title": "'WỌ ti n pafọ ninu ẹsẹ,",
        "category": "ORIN IRONUPIWADA",
        "tune": "",
        "lyrics": [
            {
                "stanza": "1",
                "lyric": "'WỌ ti n pafọ ninu ẹsẹ,\nKristi n pe ọ wa sọdọ Rẹ,\nO ti sọ ẹru ẹsẹ rẹ,\nWa sinu agbo Jesu.\n",
                "Egbe": "Kristi n pe ọ wa sọdọ Rẹ\nOun l'O ni igbala kikun,\nJesu n duro O n reti rẹ,\n'Wọ yoo ha kọ ipe Rẹ?\n"
            },
            {
                "stanza": "2",
                "lyric": "Olugbala wa s'aye yi,\nLati wa ra ọ pada,\nLọwọ ẹsẹ ati arun,\nIgbala wo lo to yii?\n",
                "Egbe": "Kristi n pe ọ wa sọdọ Rẹ\n"
            },
            {
                "stanza": "3",
                "lyric": "Bo ti wu k'ẹsẹ rẹ pọ to,\nKristi n fẹ sọ di mimọ,\nO ti pari 'sẹ gbala yi,\nO ku sọwọ rẹ, ma bọ.\n",
                "Egbe": "Kristi n pe ọ wa sọdọ Rẹ\n"
            },
            {
                "stanza": "4",
                "lyric": "Kristi n pe ọ lati ronu,\nAye mbẹ sibẹ fun ọ,\nWa, mase kiri 'nu ẹsẹ,\nAye ko lere fun ọ.\n",
                "Egbe": "Kristi n pe ọ wa sọdọ Rẹ\n"
            },
            {
                "stanza": "5",
                "lyric": "B'aye at' esu n de si ọ,\nTi 'pọnju bo ọ mọlẹ,\nWa si abẹ abo Kristi,\nNibẹ a o ri isinmi.\n",
                "Egbe": "Kristi n pe ọ wa sọdọ Rẹ\nAMIN."
            }
        ],
        "song_tag": "(FE288)"
    },
    {
        "no": 269,
        "heading": "H.C. 157. 6s. 4s.",
        "sub_heading": "Nitori oruko Re dari ese mi jii",
        "bible_verse": "- Ps. 25 : 11.",
        "intro": "",
        "title": "Kii se l'ainireti,",
        "category": "ORIN IRONUPIWADA",
        "tune": "",
        "lyrics": [
            {
                "stanza": "1",
                "lyric": "Kii se l'ainireti,\nNi mo tọ wa;\nKii se l'aini 'gbagbọ,\nNi mo kunlẹ;\nẸsẹ ti gori mi,\nEyi sa l'ẹbẹ mi,\nEyi sa l'ẹbẹ mi\nJesu ti ku."
            },
            {
                "stanza": "2",
                "lyric": "A! ẹsẹ mi pọ ju,\nO pọn kọkọ!\nAdale, adale,\nNi mo n d'ẹsẹ!\nẸsẹ aifẹran Rẹ,\nẸsẹ aigba Ọ gbọ;\nẸsẹ aigba Ọ gbọ;\nẸsẹ nlanla!"
            },
            {
                "stanza": "3",
                "lyric": "Oluwa mo jẹwọ\nEsẹ nla mi;\nO mọ bi mo ti ri,\nBi mo ti wa;\nJọ wẹ ẹsẹ mi nu!\nK' ọkan mi mọ loni,\nK'ọkan mi mọ loni,\nKi n di mimọ."
            },
            {
                "stanza": "4",
                "lyric": "Olododo ni Ọ,\nO n dariji;\nL'ẹsẹ agbelebu,\nNi mo wolẹ;\nJẹ k'ẹjẹ iwẹnu,\nẸjẹ Ọdagutan\nẸjẹ Ọdagutan,\nWẹ ọkan mi."
            },
            {
                "stanza": "5",
                "lyric": "'Gba naa, alafia,\nY'o d'ọkan mi;\n'Gba naa, n o ba Ọ rin,\nỌrẹ airi;\nEm' o f'ara ti Ọ,\nJọ ma tọ mi s'ọna\nJọ ma tọ mi s'ọna\nTiti aiye.\nAMIN."
            }
        ],
        "song_tag": "(FE289)"
    },
    {
        "no": 270,
        "heading": "C.M.S. 168 H.C. 229 7s. E.",
        "sub_heading": "Oluwa, odo Re ni mo sa pamo si",
        "bible_verse": "- Ps. 143 : 9.",
        "intro": "",
        "title": "JESU Oluf' ọkan mi,",
        "category": "ORIN IRONUPIWADA",
        "tune": "",
        "lyrics": [
            {
                "stanza": "1",
                "lyric": "JESU Oluf' ọkan mi,\nJẹ ki n sala s'aya Rẹ,\nSa t'irumi sunmọ mi,\nSa ti iji n fẹ s'oke;\nPa mi mọ, Olugbala,\nTit' iji aye y'o pin,\nTọ mi lọ s'ebute Rẹ,\nNikẹhin gba ọkan mi."
            },
            {
                "stanza": "2",
                "lyric": "Abo mi, emi ko ni,\nIwọ lọkan mi rọ mọ;\nMa f'emi nikan silẹ,\nGba mi, si tu mi ninu;\nIwọ ni mo gbẹkẹle,\nIwọ n'iranlọwọ mi;\nMasai f'iyẹ apa Rẹ,\nD'abo b'ori aibo mi."
            },
            {
                "stanza": "3",
                "lyric": "Krist 'Wọ nikan ni mo fẹ,\nN'nu Rẹ, mo r'ohun gbogbo;\nGb' ẹni t'o subu dide,\nW'alaisan, at'afọju;\nOdodo l'oruko Rẹ,\nAlaisododo l'emi,\nMo kun fun ẹsẹ pupọ,\nIwọ kun fun ododo."
            },
            {
                "stanza": "4",
                "lyric": "'Wọ l'ọpọ ore-ọfẹ,\nLati fi bor' ẹsẹ mi,\nJẹ ki omi iwosan,\nWẹ inu ọkan mi mọ;\nwọ l'orisun iye,\nJẹ ki n bu n'nu Rẹ l'ọfẹ;\nRu jade n'nu ọkan mi,\nSi iye ainipẹkun.\nAMIN."
            }
        ],
        "song_tag": "(FE290)"
    },
    {
        "no": 271,
        "heading": "C.M.S. 169 H.C. 151 6 7s.",
        "sub_heading": "Emi o fi sinu palapala apata",
        "bible_verse": "- Esk. 33 : 22.",
        "intro": "",
        "title": "APATA ayeraye",
        "category": "ORIN IRONUPIWADA",
        "tune": "",
        "lyrics": [
            {
                "stanza": "1",
                "lyric": "APATA ayeraye\nSe ibi isadi mi;\nJẹ ki omi oun ẹjẹ,\nT'o n san lati iha Rẹ,\nSe iwosan f'ẹsẹ mi,\nK'o si sọ mi di mimọ"
            },
            {
                "stanza": "2",
                "lyric": "K' Ise isẹ ọwọ mi,\nLo le mu ofin Rẹ sẹ;\nB' itara mi ko l'arẹ,\nT' omije mi n san titi;\nWọn ko to fun etutu,\n'Wọ nikan l'o le gbala."
            },
            {
                "stanza": "3",
                "lyric": "Ko s'ohun ti mo mu wa,\nMo rọ mọ agbelebu;\nMo wa, k'o d'asọ bo mi,\nMo n wo Ọ fun iranwọ;\nMo wa sib' orisun ni,\nWẹ mi, Olugbala mi."
            },
            {
                "stanza": "4",
                "lyric": "'Gbati ẹmi mi ba n lọ,\nT'iku ba p'oju mi de,\nTi mba n lọ s'aye aimọ,\nTi n ri Ọ n'itẹ 'dajọ;\nApata ayeraye,\nSe ibi isadi mi.\nAMIN."
            }
        ],
        "song_tag": "(FE291)"
    },
    {
        "no": 272,
        "heading": "CMS 170 t.H.C. 167 S.M.",
        "sub_heading": "Ese ti enyin fi se ojo be, enyin onigbagbo kekere?",
        "bible_verse": "- Matt. 8 : 26.",
        "intro": "",
        "title": "SA dakẹ ọkan mi,",
        "category": "ORIN IRONUPIWADA",
        "tune": "",
        "lyrics": [
            {
                "stanza": "1",
                "lyric": "SA dakẹ ọkan mi,\nOluwa rẹ wa mbẹ;\nEni t'o ti se ileri,\nYoo fẹ mu u sẹ."
            },
            {
                "stanza": "2",
                "lyric": "Oun ti fa Ọ lọwọ,\nO mu ọ de 'hin yi;\nY'o pa ọ mọ la ewu ja,\nTit' opin aye rẹ."
            },
            {
                "stanza": "3",
                "lyric": "Nigbat' iwọ ti bọ,\nSinu wahala ri,\nIgba rẹ naa ki Oun ha gbọ,\nT'o si yọ ọ kuro?"
            },
            {
                "stanza": "4",
                "lyric": "B'ọna ko tilẹ dan,\nYoo mu ọ de 'le;\nSa ti wahala aye tan,\nO san fun gbogbo rẹ.\nAMIN."
            }
        ],
        "song_tag": "(FE292)"
    },
    {
        "no": 273,
        "heading": "C.M.S. 171 H.C. 149 C.M.",
        "sub_heading": "Ongbe Olorun ngbe okan",
        "bible_verse": "- Ps. 42 : 2.",
        "intro": "",
        "title": "Bi agbọnrin ti n mi hẹlẹ,",
        "category": "ORIN IRONUPIWADA",
        "tune": "",
        "lyrics": [
            {
                "stanza": "1",
                "lyric": "Bi agbọnrin ti n mi hẹlẹ,\nS'ipa odo omi;\nBẹni ọkan mi n mi si Ọ,\nIwọ Ọlọrun mi."
            },
            {
                "stanza": "2",
                "lyric": "Orungbẹ Rẹ n gbẹ ọkan mi,\nỌlọrun alaye;\nNigbawo ni n o r'Oju Rẹ,\nỌlọrun Ọlanla?"
            },
            {
                "stanza": "3",
                "lyric": "Ọkan mi o se rẹwẹsi?\nGbẹkẹle Ọlọrun;\nẸni ti y'o sọ ẹkun rẹ,\nD'orin ayọ fun ọ."
            },
            {
                "stanza": "4",
                "lyric": "Y'o ti pẹ to, Ọlọrun mi,\nTi n o d'ẹni 'gbagbẹ?\nT'a o ma ti mi sihin, sọhun,\nB'ẹni ko ni 'bugbe?"
            },
            {
                "stanza": "5",
                "lyric": "Ọkan mi o se rẹwẹsi?\nGbagbọ 'wọ o si kọ,\nOrin iyin s'Ọlọrun rẹ,\nOrisun ẹmi rẹ.\nAMIN."
            }
        ],
        "song_tag": "(FE293)"
    },
    {
        "no": 274,
        "heading": "",
        "sub_heading": "Anu ni emi nfe",
        "bible_verse": "- Matt. 9 : 13.",
        "intro": "",
        "title": "B'ẸRU ẹsẹ rẹ ba n wọ ọ lọrun,",
        "category": "ORIN IRONUPIWADA",
        "tune": "",
        "lyrics": [
            {
                "stanza": "1",
                "lyric": "B'ẸRU ẹsẹ rẹ ba n wọ ọ lọrun,\nPe Jesu wọle ọkan rẹ;\nB'o n daniyan isọji ọkan rẹ,\nPe Jesu wọle ọkan rẹ.\n",
                "Egbe": "Le 'yemeji rẹ sọnu,\nBa Oluwa rẹ laja;\nSi ọkan rẹ paya fun,\nPe Jesu wọle ọkan rẹ.\n"
            },
            {
                "stanza": "2",
                "lyric": "Bi o ba n wa iwẹnumọ kiri,\nPe Jesu wọle ọkan rẹ;\nOni 'wẹnumọ ko jina si ọ,\nPe Jesu wọle ọkan rẹ.\n",
                "Egbe": "Le 'yemeji rẹ sọnu,\n"
            },
            {
                "stanza": "3",
                "lyric": "B' igbi wahala ba n gba ọ kiri\nPe Jesu wọle ọkan rẹ;\nB'afo ba wa ti aye ko le di,\nPe Jesu wọle ọkan rẹ.\n",
                "Egbe": "Le 'yemeji rẹ sọnu,\n"
            },
            {
                "stanza": "4",
                "lyric": "Bi ọrẹ t'o gbẹkẹle ba da ọ,\nPe Jesu wọle ọkan rẹ;\nBi o n fẹ wọ agbala isinmi,\nPe Jesu wọle ọkan rẹ.\n",
                "Egbe": "Le 'yemeji rẹ sọnu,\n"
            },
            {
                "stanza": "5",
                "lyric": "B' o nfe korin awon alabukun,\n Pe Jesu wole okan re;\n bi o nfe wo agbala isimi,\n Pe Jesu wole okan re.\nAMIN.",
                "Egbe": "Le 'yemeji rẹ sọnu,\nAMIN."
            }
        ],
        "song_tag": "(FE294)"
    },
    {
        "no": 275,
        "heading": "C.M.S. 148 t.H.C. 94 S.M.",
        "sub_heading": "Wa enia mi",
        "bible_verse": "- Isa. 26 : 20.",
        "intro": "",
        "title": "",
        "category": "ORIN IRONUPIWADA",
        "tune": "",
        "lyrics": [
            {
                "stanza": "1",
                "lyric": "BABA wa ọrun ń pe,\nKristi  ń pe wa sọdọ Rẹ;\nỌrẹ wa pẹlu wọn o dun,\n'Dapọ wa  y'o s'ọwọn."
            },
            {
                "stanza": "2",
                "lyric": "Ọlọrun ń kanu mi;\nO dar'ẹsẹ mi ji,\nOlodumare s'ọkan mi,\nO f'ọgbọn tọ 'pa mi."
            },
            {
                "stanza": "3",
                "lyric": "Ẹbun Rẹ ti pọ to!\nO l'ọpọ isura,\nT'a t'owo Olugbala pin,\nTi a f'ẹjẹ rẹ ra!"
            },
            {
                "stanza": "4",
                "lyric": "Jesu, Ori 'ye mi,\nMo fi 'bukun fun Ọ;\nAlagbawi lọdọ Baba,\nAsaju lọdọ Rẹ"
            },
            {
                "stanza": "5",
                "lyric": "Ọkan at'ifẹ mi,\nẸ duro jẹ nihin;\t\nTiti 'dapọ yoo fi kun,\nL'oke ọrun l'ọhun.\nAMIN."
            }
        ],
        "song_tag": "(FE295)"
    },
    {
        "no": 276,
        "heading": "H.C. 2nd Ed., 106 or t.H.C. 552 L.M.",
        "sub_heading": "On yio joba lati okun de okun",
        "bible_verse": "- Ps. 72 : 8.",
        "intro": "",
        "title": "Jesu yoo jọba ni gbogbo",
        "category": "ORIN IRONUPIWADA",
        "tune": "",
        "lyrics": [
            {
                "stanza": "1",
                "lyric": "Jesu yoo jọba ni gbogbo\nIbi t'a ba le ri orun;\n'Jọba Rẹ yo tan kakiri,\n'Jọba Rẹ ki y'o nipẹkun."
            },
            {
                "stanza": "2",
                "lyric": "Oun l'a o ma gbadura si,\nAwọn Ọba yoo pe l'Ọba;\nOrukọ Rẹ b'orun didun,\nY'o ba ẹbọ oorọ goke."
            },
            {
                "stanza": "3",
                "lyric": "Gbogbo oniruru ede,\nY'o fi 'fẹ Rẹ kọrin didun,\nAwọn ọmọde o jẹwọ,\nPe, 'bukun wọn t'ọdọ Rẹ wa."
            },
            {
                "stanza": "4",
                "lyric": "'Bukun pọ nibi t'Oun jọba;\nA tu awọn onde silẹ,\nAwọn alarẹ ri isinmi;\nAlaini si ri 'bukun gba."
            },
            {
                "stanza": "5",
                "lyric": "Ki  gbogbo ẹda k'o dide,\nKi wọn f'ọla fun Ọba wa;\nK'Angel' tun wa t'awọn t'orin,\nKi gbogb' ayé jumọ gberin. \nAMIN."
            }
        ],
        "song_tag": "(FE296)"
    },
    {
        "no": 277,
        "heading": "H.C. 117 6s.",
        "sub_heading": "Ijoba re de",
        "bible_verse": "- Matt. 6 : 10.",
        "intro": "",
        "title": "KRIST', ki 'jọba Rẹ de,",
        "category": "ORIN IRONUPIWADA",
        "tune": "",
        "lyrics": [
            {
                "stanza": "1",
                "lyric": "KRIST', ki 'jọba Rẹ de,\nKi asẹ Rẹ bẹrẹ;\nF'ọpa-irin Rẹ fọ,\nGbogbo ipa ẹsẹ."
            },
            {
                "stanza": "2",
                "lyric": "Ijọba ifẹ da,\nAti t'alafia?\nGba wo ni irira,\nYoo tan bi t'ọrun?"
            },
            {
                "stanza": "3",
                "lyric": "Akoko naa ha da,\nT'ọtẹ yoo pari,\nIka at'irẹjẹ,\nPẹlu ifẹkufẹ?"
            },
            {
                "stanza": "4",
                "lyric": "Oluwa jọ, dide,\nWa n'nu agbara Rẹ:\nFi ayọ fun awa,\nTi o n s'aferi Rẹ."
            },
            {
                "stanza": "5",
                "lyric": "Ẹda ń gan ookọ Rẹ,\nKoko ń jẹ agbo Rẹ;\nIwa 'tiju pupọ,\nNfihan pe'fẹ tutu."
            },
            {
                "stanza": "6",
                "lyric": "Okun bolẹ sibẹ,\nNi ilẹ Keferi;\nDide 'Rawọ oorọ,\nDide, mase wọ mọ."
            }
        ],
        "song_tag": "(FE297)"
    },
    {
        "no": 278,
        "heading": "CMS 156, t.H.C. 182 CM",
        "sub_heading": "Pa oju Re mo kuro lara ese mi",
        "bible_verse": "- Ps. 51 : 90.",
        "intro": "",
        "title": "RO ipọnju mi, Oluwa,",
        "category": "ORIN IRONUPIWADA",
        "tune": "",
        "lyrics": [
            {
                "stanza": "1",
                "lyric": "RO ipọnju mi, Oluwa,\nRan iranlọwọ Rẹ!\nỌkan mi daku fun 'gbala,\nIsẹ mi ki o pin?"
            },
            {
                "stanza": "2",
                "lyric": "Mo ri pe o dara fun mi,\nBi baba mi na mi:\nIya mu mi ko ofin Rẹ;\nKi ń gbẹkẹ mi le Ọ."
            },
            {
                "stanza": "3",
                "lyric": "Mo mọ pe idajọ Rẹ to,\nBi o tilẹ muna;\nIpọnju ti mo f'ori ti,\nO ti ọdọ Rẹ wa."
            },
            {
                "stanza": "4",
                "lyric": "K'emi to m'ọwọ ina Rẹ,\nEmi a ma sina;\nSugbọn bi mo ti k'ọrọ Rẹ;\nEmi ko sako mọ.\nAMIN."
            }
        ],
        "song_tag": "(FE298)"
    },
    {
        "no": 279,
        "heading": "CMS 493, H.C. 460 C.M.",
        "sub_heading": "Awon omode si nke ninu tempili wipe, Hosanna si omo Dafidi.",
        "bible_verse": "- Matt. 21 : 15",
        "intro": "",
        "title": "HOSANNA! ẹ kọrin soke,",
        "category": "ORIN IRONUPIWADA",
        "tune": "",
        "lyrics": [
            {
                "stanza": "1",
                "lyric": "HOSANNA! ẹ kọrin soke,\nS'Ọmọ nla Dafidi,\nPẹlu Kerub ati Seraf,\nK'a yin Ọm-Ọlọrun."
            },
            {
                "stanza": "2",
                "lyric": "Hosanna! eyi na nikan,\nL'ahọn wa le ma kọ,\nIwọ ki o kẹgan ewe,\nTi ń kọrin iyin Rẹ."
            },
            {
                "stanza": "3",
                "lyric": "Hosanna! Alufa Ọba,\nẸbun Rẹ ti pọ to!\nẸjẹ Rẹ lo jẹ iye wa,\nỌrọ Rẹ ni Ounjẹ wa."
            },
            {
                "stanza": "4",
                "lyric": "Hosanna! Baba, awa mu\nỌrẹ wa wa fun Ọ,\nKi se wura oun ojia,\nBikose ọkan wa."
            },
            {
                "stanza": "5",
                "lyric": "Hosanna! Jesu, lẹkan ri,\nO yin awọn ewe;\nSaanu fun wa si f'eti si,\nOrin awa ewe."
            },
            {
                "stanza": "6",
                "lyric": "Jesu, b'O ba ra wa pada,\nT'a si wọ 'jọba Rẹ;\nA o fi harpu wura kọ,\nHosanna titi lai.\nAMIN."
            }
        ],
        "song_tag": "(FE299)"
    },
    {
        "no": 280,
        "heading": "T.H.C 150 C.M.",
        "sub_heading": "Gbogbo adura mi Oluwa",
        "bible_verse": "- Ps. 102 : 1",
        "intro": "",
        "title": "BABA alanu t'o fẹ wa,",
        "category": "ORIN IRONUPIWADA",
        "tune": "",
        "lyrics": [
            {
                "stanza": "1",
                "lyric": "BABA alanu t'o fẹ wa,\nMo gb'ọkan mi si Ọ;\nIpa Rẹ t'o pọ l'o gba wa;\nAwa ń kọrin si Ọ."
            },
            {
                "stanza": "2",
                "lyric": "Tirẹ papa l'awa fe se,\nGb'ọkan wa fun ẹbọ;\nO da wa, o si tun wa bi,\nA f'ara wa fun Ọ."
            },
            {
                "stanza": "3",
                "lyric": "Ẹmi Mimọ, wa sọdọ mi,\nF'ifẹ Oluwa han;\nFun mi k'emi k'o le ma rin,\nN'ifẹ Oluwa mi.\nAMIN."
            }
        ],
        "song_tag": "(FE300)"
    },
    {
        "no": 281,
        "heading": "C.M.S. 579 C.M.",
        "sub_heading": "Jesu, Baba, sanu fun wa.",
        "bible_verse": "- Luk. 17 : 13",
        "intro": "",
        "title": "ẸSẸ mi pọ bi irawọ,",
        "category": "ORIN IRONUPIWADA",
        "tune": "",
        "lyrics": [
            {
                "stanza": "1",
                "lyric": "ẸSẸ mi pọ bi irawọ,\nBi 'yanrin let' okun,\nSugbọn iyọnu Ọlọrun,\nO p'apọju bẹ lọ"
            },
            {
                "stanza": "2",
                "lyric": "Manase, Paul oun Magdalen,\nIwọ dariji wọn;\nMo ti ka mo si gbagbọ pe,\nO ti dariji mi.\nAMIN"
            }
        ],
        "song_tag": "(FE301)"
    },
    {
        "no": 282,
        "heading": "C.M.S. 578 K. 616 8s 7s.",
        "sub_heading": "Ife ni Olorun",
        "bible_verse": "- I John 4 : 8",
        "intro": "",
        "title": "IFẸ l'Ọlọrun, anu Rẹ,",
        "category": "ORIN IRONUPIWADA",
        "tune": "",
        "lyrics": [
            {
                "stanza": "1",
                "lyric": "IFẸ l'Ọlọrun, anu Rẹ,\nTan si ọna wa gbogbo;\nO fun wa ni alafia,\nIfẹ ni Ọlọrun wa."
            },
            {
                "stanza": "2",
                "lyric": "Iku n doro pupọpupọ,\nEniyan si n dibajẹ,\nSugbọn anu Rẹ wa titi,\nIfẹ ni Ọlọrun wa"
            },
            {
                "stanza": "3",
                "lyric": "Lakoko t'o dab'o sokun,\nA ń ri Ore Rẹ daju,\nO tan imọlẹ Rẹ fun wa,\nIfẹ ni Ọlọrun wa."
            },
            {
                "stanza": "4",
                "lyric": "O sọ 'reti, at'itunu,\nMọ aniyan ayé wa,\nOgo Rẹ ń tan nibi gbogbo,\nIfẹ ni Ọlọrun wa\nAMIN."
            }
        ],
        "song_tag": "(FE302)"
    },
    {
        "no": 283,
        "heading": "C.M.S. 147 H.C. 154. C.M.",
        "sub_heading": "Oluwa, ranti mi",
        "bible_verse": "- Luk 23 : 42",
        "intro": "",
        "title": "IWỌ lọw'ẹni t'ire ń san",
        "category": "ORIN IRONUPIWADA",
        "tune": "",
        "lyrics": [
            {
                "stanza": "1",
                "lyric": "IWỌ lọw'ẹni t'ire ń san\nMo gb'ọkan mi si Ọ;\nN'ibanujẹ at'isẹ mi,\nOluwa, ranti mi."
            },
            {
                "stanza": "2",
                "lyric": "'Gba mo n kerora l'ọkan mi,\nT'ẹsẹ wo mi l'ọrun:\nDari gbogbo ẹsẹ ji mi,\nNi ifẹ, ranti mi."
            },
            {
                "stanza": "3",
                "lyric": "'Gba 'danwo kikan yi mi kan,\nTi ibi le mi ba;\nOluwa, fun mi l'agbara,\nFun rere, ranti mi."
            },
            {
                "stanza": "4",
                "lyric": "Bi 'tiju at'ẹgan ba de,\n'Tori orukọ Rẹ:\nN ó yo s'e gan, n ó gba t'iju\nB'Iwọ ba ranti mi."
            },
            {
                "stanza": "4",
                "lyric": "Bi 'tiju at'ẹgan ba de,\n'Tori orukọ Rẹ:\nN ó yo s'e gan, n ó gba t'iju\nB'Iwọ ba ranti mi."
            },
            {
                "stanza": "5",
                "lyric": "Oluwa 'gba iku de,\nEm' o sa ku dandan;\nK'eyi j'adura gbẹhin mi,\nOluwa, ranti mi.\nAMIN."
            }
        ],
        "song_tag": "(FE303)"
    },
    {
        "no": 284,
        "heading": "C.M.S. 184 K 151. t.H.C. 147 C.M.",
        "sub_heading": "kristi at' Aaroni",
        "bible_verse": "- Luk 23 : 42",
        "intro": "",
        "title": "",
        "category": "ORIN IRONUPIWADA",
        "tune": "",
        "lyrics": [
            {
                "stanza": "1",
                "lyric": "JESU, l'ara Rẹ l'awa ń wo\nẸgbẹgbẹrun ogo;\nJu t'okuta iyebiye,\nT'agbada Aaroni."
            },
            {
                "stanza": "2",
                "lyric": "Wọn ko le sai ko rubọ na,\nFun ẹsẹ ara wọn,\nIwa Rẹ pe, ko l'abawọn,\nMimọ si l'Ẹda Rẹ."
            },
            {
                "stanza": "3",
                "lyric": "Jesu Ọba ogo gunwa,\nL'oke Sion t'ọrun;\nBi Ọdọ-aguntan t'a pa,\nBi Alufa nla wa."
            },
            {
                "stanza": "4",
                "lyric": "Alagbawi lọdọ Baba,\nTi y'o wa titi lai;\nGb'ẹjọ rẹ fun 'wọ ọkan mi,\nGb'ore ọfẹ Baba.\nAMIN"
            }
        ],
        "song_tag": "(FE304)"
    },
    {
        "no": 285,
        "heading": "C.H. 40. t.H.C. 266. L.M.",
        "sub_heading": "Bi enyin o ba gbo ohun re, e ma se aiya nyin le",
        "bible_verse": "- Ps. 95 : 7,8.",
        "intro": "",
        "title": "Mura, ẹlẹsẹ, lati gbọn,",
        "category": "ORIN IRONUPIWADA",
        "tune": "",
        "lyrics": [
            {
                "stanza": "1",
                "lyric": "Mura, ẹlẹsẹ, lati gbọn,\nMa duro de ọjọ ọla;\nNiwọn b'o ti kẹgan ọgbọn,\nBẹ l'o si sọrọ lati ri."
            },
            {
                "stanza": "2",
                "lyric": "Mura lati bere anu,\nMa duro de ọjọ ọla;\nKi igba rẹ ko ma ba tan,\nKi ọjọ alẹ yi to tan."
            },
            {
                "stanza": "3",
                "lyric": "Mura elese k'o pada,\nMa duro de ojo ola;\nNitori k' egun ma b o,\nK' ojo ola k' o to bere."
            },
            {
                "stanza": "4",
                "lyric": "Mura lati gba ibukun,\nMa duro de ọjọ ọla;\nKi fitila rẹ ma ba ku,\nK'isẹ rere rẹ to bẹrẹ."
            },
            {
                "stanza": "5",
                "lyric": "Oluwa, y'ẹlẹsẹ pada,\nJi kuro ninu were rẹ ;\nMa jẹ k'o tapa s'imọ Rẹ,\nK'o ma f'ẹgbẹ rẹ se 'lọra.\nAMIN."
            }
        ],
        "song_tag": "(FE304)"
    }
]